mutuazones/__init__.py
mutuazones/db.py
mutuazones/util.py
mutuazones-0.1.1.dist-info/METADATA
mutuazones-0.1.1.dist-info/WHEEL
mutuazones-0.1.1.dist-info/top_level.txt
mutuazones-0.1.1.dist-info/RECORD
