Metadata-Version: 2.1
Name: mutuazones
Version: 0.1.1
Summary: Mensajes de depuración
Home-page: https://gitlab.com/mutuatfe/smartflow/mutuazones.git
Author: Carlos López Pérez
Author-email: carlos.lopez@mutuatfe.com
License: UNKNOWN
Platform: UNKNOWN
Classifier: Programming Language :: Python :: 3
Classifier: License :: OSI Approved :: MIT License
Classifier: Operating System :: OS Independent
